<ns2:doValidatePasswordRq xmlns:log="http://itau.com.co/services/common/auditory/v2/schemas" xmlns="http://schemas.xmlsoap.org/soap/envelope/" xmlns:ns2="http://itau.com.co/services/security/validatepassword/v1/schemas">
	<ns2:HeaderRequest>
		<MessageHeader xmlns="http://itau.com.co/commoncannonical/v2/schemas">
			<MessageKey>
				<integrationId/>
				<requestVersion/>
				<requestUUID>ba20c628-b3ea-4b00-a21c-33f6596ad6ae</requestUUID> <!-- generar un UUID al consumir el servicio-->
			</MessageKey>
			<MessageInfo>
				<dateTime>2020-01-30T13:35:00.170-05:00</dateTime> <!-- dateTime de consumo -->
				<systemId/>
				<originatorName>SSO</originatorName>	<!-- Inicialmente para determinar que se está haciendo login desde SSO fijo este valor -->
				<originatorType>41</originatorType>		<!-- Valor 41 fijo para canales digitales -->
				<terminalId>10.186.25.10</terminalId>	<!-- IP de inicio de sesion -->
			</MessageInfo>
		</MessageHeader>
	</ns2:HeaderRequest>
	<ns2:CustId>
		<ns1:custLoginId xmlns:ns1="http://itau.com.co/commoncannonical/v2/schemas">U8300383191_8300383191</ns1:custLoginId>
	</ns2:CustId>
	<ns2:pswd>Z43969828758183123449903117774869903935938644223236930332884220308728713706636l7969698661034114270347621156745969218493023012152295802380940786283439200593</ns2:pswd>
</ns2:doValidatePasswordRq>

<!--
Para validar que la respuesta sea correcta Status/statusCode = 000 and Status/serverStatusCode = 00
Los datos para generar el token SignOnCustomerInfo/SignOnCustomerInfoRecord/CustPermId (numero de documento) y SignOnCustomerInfo/SignOnCustomerInfoRecord/CustIdType (tipo de documento)
Generar un header con nombre token_client_id concantenando numero y tipo de documento ejemplo: 8300383191_3
-->

<response>
	<Header xmlns:log="http://itau.com.co/services/common/auditory/v2/schemas" xmlns="http://schemas.xmlsoap.org/soap/envelope/"/>
	<val:doValidatePasswordRs xmlns:log="http://itau.com.co/services/common/auditory/v2/schemas" xmlns="http://schemas.xmlsoap.org/soap/envelope/" xmlns:val="http://itau.com.co/services/security/validatepassword/v1/schemas">
		<val:HeaderResponse>
			<com:MessageHeader xmlns:com="http://itau.com.co/commoncannonical/v2/schemas">
				<com:MessageKey>
					<com:integrationId>PortalPJ</com:integrationId>
					<com:requestVersion/>
					<com:requestUUID>ba20c628-b3ea-4b00-a21c-33f6596ad6af</com:requestUUID>
				</com:MessageKey>
				<com:MessageInfo>
					<com:dateTime>2020-01-30T13:35:00.170-05:00</com:dateTime>
					<com:systemId>Itau</com:systemId>
					<com:originatorName>PORTAL</com:originatorName>
					<com:originatorType>41</com:originatorType>
					<com:terminalId>10.186.25.10</com:terminalId>
					<com:terminalType>PORTAL</com:terminalType>
					<com:bankIdType>Itau</com:bankIdType>
					<com:bankId>14</com:bankId>
				</com:MessageInfo>
				<com:TrnInfoList>
					<com:TrnInfo>
						<com:trnCode/>
						<com:trnSrc>0018</com:trnSrc>
					</com:TrnInfo>
				</com:TrnInfoList>
			</com:MessageHeader>
			<com:Status xmlns:com="http://itau.com.co/commoncannonical/v2/schemas">
				<com:statusCode>000</com:statusCode>
				<com:serverStatusCode>00</com:serverStatusCode>
				<com:severity>Info</com:severity>
				<com:statusDesc>Autenticacion exitosa</com:statusDesc>
			</com:Status>
		</val:HeaderResponse>
		<val:SignOnCustomerInfo>
			<com:SignOnCustomerInfoRecord xmlns:com="http://itau.com.co/commoncannonical/v2/schemas">
				<com:ChangePwdFlag>0</com:ChangePwdFlag>
				<com:SessionId>1335003163191</com:SessionId>
				<com:UserType>W</com:UserType>
				<com:BankIdType>EMP</com:BankIdType>
				<com:UserIdType>3</com:UserIdType>
				<com:UserPermId>8300383191</com:UserPermId>
				<com:UserName>MARIA BARON</com:UserName>
				<com:CompanyAdminRole>S</com:CompanyAdminRole>
				<com:Language>E</com:Language>
				<com:CustIdType>3</com:CustIdType>
				<com:CustPermId>8300383191</com:CustPermId>
				<com:TrxPswFlag>N</com:TrxPswFlag>
				<com:LastLogonDt>2020-01-30T13:34:30.186-05:00</com:LastLogonDt>
				<com:CustName>TROTAMUNDOS S A</com:CustName>
				<com:ContractSignFlag>S</com:ContractSignFlag>
				<com:SignOnCustCostCenterId/>
				<com:DaysToPwdChange>8</com:DaysToPwdChange>
				<com:DaysToPwdTxChange>0</com:DaysToPwdTxChange>
				<com:EmailAddr>miguel.guaqueta@itau.co</com:EmailAddr>
			</com:SignOnCustomerInfoRecord>
		</val:SignOnCustomerInfo>
	</val:doValidatePasswordRs>
</response>
